se_utils/__init__.py
se_utils/__main__.py
se_utils/exceptions.py
se_utils/backend/__init__.py
se_utils/backend/milvus/__init__.py
se_utils/backend/milvus/conf.py
se_utils/backend/milvus/core.py
similarity_engine_utils-0.1.2.dist-info/LICENSE
similarity_engine_utils-0.1.2.dist-info/METADATA
similarity_engine_utils-0.1.2.dist-info/WHEEL
similarity_engine_utils-0.1.2.dist-info/entry_points.txt
similarity_engine_utils-0.1.2.dist-info/top_level.txt
similarity_engine_utils-0.1.2.dist-info/RECORD
