Metadata-Version: 2.1
Name: similarity-engine-utils
Version: 0.1.2
Summary: Similarity engine utils
Author-email: "Dima S." <dima.sakovich@gmail.com>
License: MIT License
Project-URL: Homepage, https://github.com/dsakovych/similarity-engine-utils
Project-URL: Bug Tracker, https://github.com/dsakovych/similarity-engine-utils/issues
Keywords: se_utils
Classifier: License :: OSI Approved :: MIT License
Classifier: Programming Language :: Python
Classifier: Programming Language :: Python :: 3
Requires-Python: >=3.8
License-File: LICENSE
Requires-Dist: pymilvus (>=2.2.2)
Requires-Dist: tomli ; python_version < "3.11"
Provides-Extra: dev
Requires-Dist: pytest ; extra == 'dev'
Requires-Dist: isort ; extra == 'dev'
